coininfo_atemon/__init__.py
coininfo_atemon/info.py
coininfo_atemon-0.1.dist-info/METADATA
coininfo_atemon-0.1.dist-info/WHEEL
coininfo_atemon-0.1.dist-info/top_level.txt
coininfo_atemon-0.1.dist-info/RECORD
