Metadata-Version: 2.1
Name: coininfo-atemon
Version: 0.1
Requires-Dist: requests ==2.31.0
